{
  "tool_name": "get_all_financial_statements",
  "args": {
    "ticker": "MSFT",
    "period": "annual",
    "limit": 1
  },
  "summary": "[object AIMessage]",
  "timestamp": "2025-12-01T22:01:51.051Z",
  "task_id": 2,
  "result": "{\"income_statements\":[{\"ticker\":\"MSFT\",\"report_period\":\"2025-06-30\",\"fiscal_period\":\"2025-FY\",\"period\":\"annual\",\"currency\":\"USD\",\"revenue\":281724000000,\"cost_of_revenue\":87831000000,\"gross_profit\":193893000000,\"operating_expense\":65365000000,\"selling_general_and_administrative_expenses\":32877000000,\"research_and_development\":32488000000,\"operating_income\":128528000000,\"interest_expense\":2385000000,\"ebit\":126012000000,\"income_tax_expense\":21795000000,\"net_income_discontinued_operations\":0,\"net_income_non_controlling_interests\":0,\"net_income\":101832000000,\"net_income_common_stock\":101832000000,\"preferred_dividends_impact\":0,\"consolidated_income\":101832000000,\"earnings_per_share\":13.7,\"earnings_per_share_diluted\":13.64,\"dividends_per_common_share\":3.24,\"weighted_average_shares\":7433000000,\"weighted_average_shares_diluted\":7465000000}],\"balance_sheets\":[{\"ticker\":\"MSFT\",\"report_period\":\"2025-06-30\",\"fiscal_period\":\"2025-FY\",\"period\":\"annual\",\"currency\":\"USD\",\"total_assets\":619003000000,\"current_assets\":191131000000,\"cash_and_equivalents\":30242000000,\"inventory\":938000000,\"current_investments\":64323000000,\"trade_and_non_trade_receivables\":69905000000,\"non_current_assets\":427872000000,\"property_plant_and_equipment\":229789000000,\"goodwill_and_intangible_assets\":142113000000,\"investments\":79728000000,\"non_current_investments\":15405000000,\"tax_assets\":0,\"total_liabilities\":275524000000,\"current_liabilities\":141218000000,\"current_debt\":2999000000,\"trade_and_non_trade_payables\":27724000000,\"deferred_revenue\":67265000000,\"deposit_liabilities\":0,\"non_current_liabilities\":134306000000,\"non_current_debt\":57589000000,\"tax_liabilities\":36032000000,\"shareholders_equity\":343479000000,\"retained_earnings\":237731000000,\"accumulated_other_comprehensive_income\":-3347000000,\"outstanding_shares\":7432543865,\"total_debt\":60588000000}],\"cash_flow_statements\":[{\"ticker\":\"MSFT\",\"report_period\":\"2025-06-30\",\"fiscal_period\":\"2025-FY\",\"period\":\"annual\",\"currency\":\"USD\",\"net_income\":101832000000,\"depreciation_and_amortization\":34153000000,\"share_based_compensation\":11974000000,\"net_cash_flow_from_operations\":136162000000,\"net_cash_flow_from_investing\":-72599000000,\"capital_expenditure\":-64551000000,\"property_plant_and_equipment\":-75237000000,\"business_acquisitions_and_disposals\":-5978000000,\"investment_acquisitions_and_disposals\":-4387000000,\"net_cash_flow_from_financing\":-51699000000,\"issuance_or_repayment_of_debt_securities\":-8962000000,\"issuance_or_purchase_of_equity_shares\":-16364000000,\"dividends_and_other_cash_distributions\":-24082000000,\"change_in_cash_and_equivalents\":11927000000,\"effect_of_exchange_rate_changes\":63000000,\"ending_cash_balance\":30242000000,\"free_cash_flow\":71611000000}]}"
}